proper_new/__init__.py
proper_new-0.6.dist-info/METADATA
proper_new-0.6.dist-info/WHEEL
proper_new-0.6.dist-info/entry_points.txt
proper_new-0.6.dist-info/top_level.txt
proper_new-0.6.dist-info/RECORD
