Metadata-Version: 2.4
Name: proper_new
Version: 0.6
Summary: A script to generate a new Proper project
Author-email: Juan Pablo Scaletti <juanpablo@jpscaletti.com>
License-Expression: MIT
Project-URL: repository, https://github.com/jpsca/proper-new
Classifier: Development Status :: 4 - Beta
Classifier: Environment :: Web Environment
Classifier: Intended Audience :: Developers
Classifier: Programming Language :: Python :: 3 :: Only
Classifier: Programming Language :: Python :: 3.13
Classifier: Programming Language :: Python :: 3.14
Classifier: Typing :: Typed
Requires-Python: <4,>=3.13
Requires-Dist: hecto>=2.2.1
Requires-Dist: inflection>=0.5.1
